Surya_Library_App/__init__.py
Surya_Library_App/__main__.py
Surya_Library_App/main.py
Surya_Course_generator-1.dist-info/METADATA
Surya_Course_generator-1.dist-info/WHEEL
Surya_Course_generator-1.dist-info/top_level.txt
Surya_Course_generator-1.dist-info/RECORD
