Metadata-Version: 2.1
Name: Surya_Course_generator
Version: 1
Summary: This is going to be game changer as there is no such project in this world we are going to make hardware soon for it and it's second version going to be boom
Author: Suraj sharma
Author-email: Surajsharma963472@gmail.com
Keywords: Surya,Game changer,GUI,python tutorial,Suraj,Dictionary,Library,LLAMA,AI
Requires-Dist: PyQt5
Requires-Dist: qtwidgets
Requires-Dist: PyMuPDF
Requires-Dist: webscout
Requires-Dist: fpdf
Requires-Dist: rich
